Metadata-Version: 2.4
Name: llama-index-multi-modal-llms-dashscope
Version: 0.4.1
Summary: llama-index multi modal llms dashscope integration
Author-email: Your Name <you@example.com>
License-Expression: MIT
License-File: LICENSE
Requires-Python: <4.0,>=3.9
Requires-Dist: dashscope<2,>=1.14.1
Requires-Dist: llama-index-core<0.15,>=0.13.0
Requires-Dist: llama-index-llms-dashscope<2,>=0.4.0
